atmosentry/__init__.py
atmosentry/fragments.py
atmosentry/integrator.py
atmosentry/simulation.py
atmosentry/meteoroid/__init__.py
atmosentry/meteoroid/meteoroid.py
atmosentry-0.0.7.dist-info/licenses/LICENSE
atmosentry-0.0.7.dist-info/METADATA
atmosentry-0.0.7.dist-info/WHEEL
atmosentry-0.0.7.dist-info/top_level.txt
atmosentry-0.0.7.dist-info/RECORD
