Metadata-Version: 2.4
Name: atmosentry
Version: 0.0.7
Summary: description tbd.
Home-page: https://github.com/richard17a/atmosentry
Author: Richard Anslow
Author-email: r.anslow@outlook.com
License: MIT License
License-File: LICENSE
Dynamic: author
Dynamic: author-email
Dynamic: home-page
Dynamic: license
Dynamic: license-file
Dynamic: summary
